wasilzafar/__init__.py
wasilzafar/__main__.py
wasilzafar/print_me_funcs.py
wasilzafar-0.1.5.dist-info/licenses/LICENSE.txt
wasilzafar-0.1.5.dist-info/METADATA
wasilzafar-0.1.5.dist-info/WHEEL
wasilzafar-0.1.5.dist-info/entry_points.txt
wasilzafar-0.1.5.dist-info/top_level.txt
wasilzafar-0.1.5.dist-info/RECORD
