Metadata-Version: 2.4
Name: wasilzafar
Version: 0.1.5
Summary: My first package!
Author-email: Wasil Zafar <wasil.zafar@gmail.com>
Maintainer-email: Wasil Zafar <wasil.zafar@gmail.com>
License: Copyright 2025 Wasil Zafar
Project-URL: Homepage, https://github.com/wasilzafar/itswzeepypi
Project-URL: Documentation, https://github.com/wasilzafar/itswzeepypi/README.md
Keywords: Wasil
Classifier: Programming Language :: Python :: 3.9
Classifier: Programming Language :: Python :: Implementation :: CPython
Classifier: License :: OSI Approved :: BSD License
Classifier: Intended Audience :: Developers
Classifier: Operating System :: POSIX :: Linux
Classifier: Operating System :: Microsoft :: Windows
Classifier: Operating System :: MacOS
Classifier: Operating System :: MacOS :: MacOS X
Requires-Python: >=3.9
License-File: LICENSE.txt
Dynamic: license-file
